face_recognition_service/__init__.py
face_recognition_service/api.py
face_recognition_service/cli.py
face_recognition_service/face_engine.py
face_recognition_service/__pycache__/__init__.cpython-36.pyc
face_recognition_service/__pycache__/api.cpython-36.pyc
face_recognition_service/__pycache__/cli.cpython-36.pyc
face_recognition_service/__pycache__/face_engine.cpython-36.pyc
face_recognition_service/models/__init__.py
face_recognition_service/models/database.py
face_recognition_service/models/face.py
face_recognition_service/models/__pycache__/__init__.cpython-36.pyc
face_recognition_service/models/__pycache__/database.cpython-36.pyc
face_recognition_service/models/__pycache__/face.cpython-36.pyc
face_recognition_service/resources/__init__.py
face_recognition_service/resources/comparison.py
face_recognition_service/resources/configuration.py
face_recognition_service/resources/conversion.py
face_recognition_service/resources/encodings.py
face_recognition_service/resources/example_page.py
face_recognition_service/resources/__pycache__/__init__.cpython-36.pyc
face_recognition_service/resources/__pycache__/comparison.cpython-36.pyc
face_recognition_service/resources/__pycache__/configuration.cpython-36.pyc
face_recognition_service/resources/__pycache__/conversion.cpython-36.pyc
face_recognition_service/resources/__pycache__/encodings.cpython-36.pyc
face_recognition_service/resources/__pycache__/example_page.cpython-36.pyc
face_recognition_service/static/css/app.css
face_recognition_service/static/css/bootstrap.min.css
face_recognition_service/static/js/app.js
face_recognition_service/static/js/bootstrap.min.js
face_recognition_service/static/js/jquery-3.4.1.min.js
face_recognition_service/static/js/popper.min.js
face_recognition_service/templates/index.html
face_recognition_service/util/__init__.py
face_recognition_service/util/serialize.py
face_recognition_service/util/singleton.py
face_recognition_service/util/__pycache__/__init__.cpython-36.pyc
face_recognition_service-0.1.4.dist-info/AUTHORS.rst
face_recognition_service-0.1.4.dist-info/LICENSE
face_recognition_service-0.1.4.dist-info/METADATA
face_recognition_service-0.1.4.dist-info/WHEEL
face_recognition_service-0.1.4.dist-info/entry_points.txt
face_recognition_service-0.1.4.dist-info/top_level.txt
face_recognition_service-0.1.4.dist-info/RECORD
