Metadata-Version: 1.1
Name: face-recognition-service
Version: 0.1.4
Summary: face recognition api service
Home-page: https://github.com/kedpter/face_recognition_service
Author: UNKNOWN
Author-email: 790476448@qq.com
License: MIT license
Keywords: face_recognition_service
Platform: UNKNOWN
Classifier: Development Status :: 2 - Pre-Alpha
Classifier: Intended Audience :: Developers
Classifier: License :: OSI Approved :: MIT License
Classifier: Natural Language :: English
Classifier: Programming Language :: Python :: 2
Classifier: Programming Language :: Python :: 2.7
Classifier: Programming Language :: Python :: 3
Classifier: Programming Language :: Python :: 3.4
Classifier: Programming Language :: Python :: 3.5
Classifier: Programming Language :: Python :: 3.6
